ethereum_light_api/__init__.py
ethereum_light_api/contracts.py
ethereum_light_api/http_api.py
ethereum_light_api/private_key.py
ethereum_light_api/raw_transaction.py
ethereum_light_api-0.1.0.dist-info/licenses/LICENSE
ethereum_light_api-0.1.0.dist-info/METADATA
ethereum_light_api-0.1.0.dist-info/WHEEL
ethereum_light_api-0.1.0.dist-info/top_level.txt
ethereum_light_api-0.1.0.dist-info/RECORD
